defender2yara/__main__.py
defender2yara/defender/__init__.py
defender2yara/defender/constant/__init__.py
defender2yara/defender/constant/ignore_threats.py
defender2yara/defender/constant/platform.py
defender2yara/defender/constant/sig_types.py
defender2yara/defender/constant/suffix.py
defender2yara/defender/constant/threat_name_prefix.py
defender2yara/defender/download.py
defender2yara/defender/signature/__init__.py
defender2yara/defender/signature/base.py
defender2yara/defender/signature/hstr.py
defender2yara/defender/signature/threat.py
defender2yara/defender/subrule/__init__.py
defender2yara/defender/subrule/hstr.py
defender2yara/defender/threat.py
defender2yara/defender/vdm.py
defender2yara/main.py
defender2yara/util/__init__.py
defender2yara/util/cabarchive.py
defender2yara/util/logging.py
defender2yara/util/pe.py
defender2yara/util/utils.py
defender2yara/yara/__init__.py
defender2yara/yara/condition.py
defender2yara/yara/rule.py
defender2yara/yara/strings.py
defender2yara-1.0.4.dist-info/METADATA
defender2yara-1.0.4.dist-info/WHEEL
defender2yara-1.0.4.dist-info/entry_points.txt
defender2yara-1.0.4.dist-info/licenses/LICENSE
defender2yara-1.0.4.dist-info/RECORD
