Metadata-Version: 2.4
Name: defender2yara
Version: 1.0.4
Summary: Convert Microsoft Defender Antivirus Signatures(VDM) to YARA rules.
License-File: LICENSE
Author: Tomoaki Tani
Requires-Python: >=3.10,<4.0
Classifier: Programming Language :: Python :: 3
Classifier: Programming Language :: Python :: 3.10
Classifier: Programming Language :: Python :: 3.11
Classifier: Programming Language :: Python :: 3.12
Classifier: Programming Language :: Python :: 3.13
Classifier: Programming Language :: Python :: 3.14
Requires-Dist: colorama (>=0.4.6,<0.5.0)
Requires-Dist: httpx (>=0.28.1,<0.29.0)
Requires-Dist: libarchive-c (>=5.1,<6.0)
Requires-Dist: pefile (>=2023.2.7,<2024.0.0)
Requires-Dist: pyexiftool (>=0.5.6,<0.6.0)
Requires-Dist: toml (>=0.10.2,<0.11.0)
Requires-Dist: tqdm (>=4.66.4,<5.0.0)
Requires-Dist: yara-python (>=4.5.1,<5.0.0)
